README.md
setup.cfg
setup.py
electrical_openapi_client_v2/__init__.py
electrical_openapi_client_v2/api_client.py
electrical_openapi_client_v2/configuration.py
electrical_openapi_client_v2/exceptions.py
electrical_openapi_client_v2/rest.py
electrical_openapi_client_v2/schemas.py
electrical_openapi_client_v2.egg-info/PKG-INFO
electrical_openapi_client_v2.egg-info/SOURCES.txt
electrical_openapi_client_v2.egg-info/dependency_links.txt
electrical_openapi_client_v2.egg-info/requires.txt
electrical_openapi_client_v2.egg-info/top_level.txt
electrical_openapi_client_v2/apis/__init__.py
electrical_openapi_client_v2/apis/path_to_api.py
electrical_openapi_client_v2/apis/tag_to_api.py
electrical_openapi_client_v2/apis/paths/__init__.py
electrical_openapi_client_v2/apis/paths/history_.py
electrical_openapi_client_v2/apis/paths/history_id_.py
electrical_openapi_client_v2/apis/tags/__init__.py
electrical_openapi_client_v2/apis/tags/history_api.py
electrical_openapi_client_v2/model/__init__.py
electrical_openapi_client_v2/model/history.py
electrical_openapi_client_v2/model/paginated_history_list.py
electrical_openapi_client_v2/model/patched_history.py
electrical_openapi_client_v2/models/__init__.py
electrical_openapi_client_v2/paths/__init__.py
electrical_openapi_client_v2/paths/history_/__init__.py
electrical_openapi_client_v2/paths/history_/get.py
electrical_openapi_client_v2/paths/history_/post.py
electrical_openapi_client_v2/paths/history_id_/__init__.py
electrical_openapi_client_v2/paths/history_id_/delete.py
electrical_openapi_client_v2/paths/history_id_/get.py
electrical_openapi_client_v2/paths/history_id_/patch.py
electrical_openapi_client_v2/paths/history_id_/put.py
test/test_models/__init__.py
test/test_models/test_history.py
test/test_models/test_paginated_history_list.py
test/test_models/test_patched_history.py
test/test_paths/__init__.py
test/test_paths/test_history_/__init__.py
test/test_paths/test_history_/test_get.py
test/test_paths/test_history_/test_post.py
test/test_paths/test_history_id_/__init__.py
test/test_paths/test_history_id_/test_delete.py
test/test_paths/test_history_id_/test_get.py
test/test_paths/test_history_id_/test_patch.py
test/test_paths/test_history_id_/test_put.py