Metadata-Version: 2.1
Name: electrical-openapi-client-v2
Version: 1.0.0
Summary: Your Project API
Home-page: UNKNOWN
Author: OpenAPI Generator community
Author-email: artemtemp@mail.ru
License: UNKNOWN
Keywords: OpenAPI,OpenAPI-Generator,Your Project API
Platform: UNKNOWN
Requires-Python: >=3.7
